{
	"name": "AzureSqlTable1",
	"properties": {
		"linkedServiceName": {
			"referenceName": "AzureSqlDatabase1",
			"type": "LinkedServiceReference"
		},
		"annotations": [],
		"type": "AzureSqlTable",
		"schema": [
			{
				"name": "id",
				"type": "tinyint",
				"precision": 3
			},
			{
				"name": "product",
				"type": "nvarchar"
			},
			{
				"name": "price",
				"type": "smallint",
				"precision": 5
			},
			{
				"name": "quantity",
				"type": "tinyint",
				"precision": 3
			}
		],
		"typeProperties": {
			"schema": "dbo",
			"table": "sales"
		}
	},
	"type": "Microsoft.DataFactory/factories/datasets"
}